{"updatedAt":"","description":"'Tentei ser homem, não deu certo', diz ex-Ken Humano","uri":"http://tvefamosos.uol.com.br/noticias/redacao/2020/03/02/roddy-ex-ken-humano-festeja-transicao-tentei-ser-homem-nao-deu-certo.htm","contents":"[\n      <p>'Tentei ser homem, não deu certo', diz ex-Ken Humano</p>\n      <img src=\"https://conteudo.imguol.com.br/c/home/f5/2020/03/02/roddy-1583146121936_615x300.jpg??\" alt=\" Instagram/Reprodução\" title=\" Instagram/Reprodução\" />\n    ]","link":"[]","categories":"[]","content":"<!DOCTYPE HTML PUBLIC \"-//IETF//DTD HTML 2.0//EN\">\n<html><head>\n<title>301 Moved Permanently</title>\n</head><body>\n<h1>Moved Permanently</h1>\n<p>The document has moved <a href=\"https://tvefamosos.uol.com.br/noticias/redacao/2020/03/02/roddy-ex-ken-humano-festeja-transicao-tentei-ser-homem-nao-deu-certo.htm\">here</a>.</p>\n</body></html>\n","title":"Transição | 'Tentei ser homem, não deu certo', diz ex-Ken Humano","publishedAt":""}